README.rst
setup.py
versionbump/__init__.py
versionbump/command_line.py
versionbump/filebump.py
versionbump/versionbump.py
versionbump.egg-info/PKG-INFO
versionbump.egg-info/SOURCES.txt
versionbump.egg-info/dependency_links.txt
versionbump.egg-info/entry_points.txt
versionbump.egg-info/top_level.txt